mynumpytestadd/__init__.py
mynumpytestadd-0.0.4.dist-info/METADATA
mynumpytestadd-0.0.4.dist-info/WHEEL
mynumpytestadd-0.0.4.dist-info/top_level.txt
mynumpytestadd-0.0.4.dist-info/RECORD
